<?xml version="1.0"?>
<projectProfile type="default" version="1.11.11">
  <projectDirectory>
    <projectProfileFile filesystemName=".zfproject.xml"/>
    <applicationDirectory classNamePrefix="Application_">
      <apisDirectory enabled="false"/>
      <configsDirectory>
        <applicationConfigFile type="ini"/>
      </configsDirectory>
      <controllersDirectory>
        <controllerFile controllerName="Index">
          <actionMethod actionName="index"/>
          <actionMethod actionName="bugReport"/>
          <actionMethod actionName="list"/>
          <actionMethod actionName="view"/>
        </controllerFile>
        <controllerFile controllerName="Error"/>
        <controllerFile controllerName="BugReport">
          <actionMethod actionName="index"/>
          <actionMethod actionName="reportBug"/>
          <actionMethod actionName="confirm"/>
          <actionMethod actionName="list"/>
          <actionMethod actionName="tableRow"/>
          <actionMethod actionName="edit"/>
          <actionMethod actionName="delete"/>
        </controllerFile>
        <controllerFile controllerName="User">
          <actionMethod actionName="index"/>
          <actionMethod actionName="create"/>
          <actionMethod actionName="register"/>
          <actionMethod actionName="list"/>
          <actionMethod actionName="login"/>
          <actionMethod actionName="logout"/>
          <actionMethod actionName="view"/>
        </controllerFile>
        <controllerFile controllerName="Page">
          <actionMethod actionName="index"/>
          <actionMethod actionName="create"/>
        </controllerFile>
        <controllerFile controllerName="Relationship">
          <actionMethod actionName="index"/>
          <actionMethod actionName="pending"/>
          <actionMethod actionName="form"/>
          <actionMethod actionName="request"/>
          <actionMethod actionName="reject"/>
          <actionMethod actionName="create"/>
        </controllerFile>
        <controllerFile controllerName="Status">
          <actionMethod actionName="index"/>
          <actionMethod actionName="listStatuses"/>
          <actionMethod actionName="createStatus"/>
          <actionMethod actionName="list"/>
          <actionMethod actionName="create"/>
        </controllerFile>
        <controllerFile controllerName="Debug">
          <actionMethod actionName="index"/>
        </controllerFile>
        <controllerFile controllerName="Profile">
          <actionMethod actionName="index"/>
        </controllerFile>
        <controllerFile controllerName="Document">
          <actionMethod actionName="index"/>
          <actionMethod actionName="create"/>
          <actionMethod actionName="view"/>
          <actionMethod actionName="edit"/>
        </controllerFile>
        <controllerFile controllerName="Wordlist">
          <actionMethod actionName="index"/>
        </controllerFile>
        <controllerFile controllerName="Classname">
          <actionMethod actionName="index"/>
        </controllerFile>
        <controllerFile controllerName="Search">
          <actionMethod actionName="index"/>
        </controllerFile>
        <controllerFile controllerName="Title">
          <actionMethod actionName="index"/>
        </controllerFile>
      </controllersDirectory>
      <formsDirectory>
        <formFile formName="ReportBug"/>
        <formFile formName="BugReportListTool"/>
        <formFile formName="Register"/>
        <formFile formName="Document"/>
        <formFile formName="Profile"/>
        <formFile formName="Action"/>
        <formFile formName="Login"/>
        <formFile formName="Search"/>
        <formFile formName="Search"/>
        <formFile formName="Profile\"/>
        <formFile formName="Triplet"/>
      </formsDirectory>
      <layoutsDirectory>
        <layoutScriptsDirectory>
          <layoutScriptFile layoutName="layout"/>
        </layoutScriptsDirectory>
      </layoutsDirectory>
      <modelsDirectory>
        <dbTableDirectory>
          <dbTableFile dbTableName="Bug"/>
          <dbTableFile dbTableName="User"/>
          <dbTableFile dbTableName="Page"/>
          <dbTableFile dbTableName="ContentNode"/>
          <dbTableFile dbTableName="Relationship"/>
          <dbTableFile dbTableName="Profile"/>
          <dbTableFile dbTableName="Status"/>
          <dbTableFile dbTableName="Wordlist"/>
          <dbTableFile dbTableName="Classname"/>
        </dbTableDirectory>
        <modelFile modelName="Profile"/>
        <modelFile modelName="User"/>
        <modelFile modelName="Status"/>
        <modelFile modelName="Relationship"/>
        <modelFile modelName="RelationshipMapper"/>
        <modelFile modelName="UserMapper"/>
        <modelFile modelName="ProfileMapper"/>
        <modelFile modelName="StatusMapper"/>
        <modelFile modelName="Stream"/>
        <modelFile modelName="Document"/>
        <modelFile modelName="DocumentMapper"/>
      </modelsDirectory>
      <modulesDirectory enabled="false"/>
      <viewsDirectory>
        <viewScriptsDirectory>
          <viewControllerScriptsDirectory forControllerName="Index">
            <viewScriptFile forActionName="index"/>
          </viewControllerScriptsDirectory>
          <viewControllerScriptsDirectory forControllerName="Error">
            <viewScriptFile forActionName="error"/>
          </viewControllerScriptsDirectory>
          <viewControllerScriptsDirectory forControllerName="BugReport">
            <viewScriptFile forActionName="index"/>
          </viewControllerScriptsDirectory>
          <viewControllerScriptsDirectory forControllerName="BugReport">
            <viewScriptFile forActionName="reportBug"/>
          </viewControllerScriptsDirectory>
          <viewControllerScriptsDirectory forControllerName="BugReport">
            <viewScriptFile forActionName="confirm"/>
          </viewControllerScriptsDirectory>
          <viewControllerScriptsDirectory forControllerName="BugReport">
            <viewScriptFile forActionName="list"/>
          </viewControllerScriptsDirectory>
          <viewControllerScriptsDirectory forControllerName="BugReport">
            <viewScriptFile forActionName="tableRow"/>
          </viewControllerScriptsDirectory>
          <viewControllerScriptsDirectory forControllerName="BugReport">
            <viewScriptFile forActionName="edit"/>
          </viewControllerScriptsDirectory>
          <viewControllerScriptsDirectory forControllerName="Index">
            <viewScriptFile forActionName="bugReport"/>
          </viewControllerScriptsDirectory>
          <viewControllerScriptsDirectory forControllerName="BugReport">
            <viewScriptFile forActionName="delete"/>
          </viewControllerScriptsDirectory>
          <viewControllerScriptsDirectory forControllerName="User">
            <viewScriptFile forActionName="index"/>
          </viewControllerScriptsDirectory>
          <viewControllerScriptsDirectory forControllerName="User">
            <viewScriptFile forActionName="create"/>
          </viewControllerScriptsDirectory>
          <viewControllerScriptsDirectory forControllerName="User">
            <viewScriptFile forActionName="register"/>
          </viewControllerScriptsDirectory>
          <viewControllerScriptsDirectory forControllerName="Index">
            <viewScriptFile forActionName="list"/>
          </viewControllerScriptsDirectory>
          <viewControllerScriptsDirectory forControllerName="User">
            <viewScriptFile forActionName="list"/>
          </viewControllerScriptsDirectory>
          <viewControllerScriptsDirectory forControllerName="User">
            <viewScriptFile forActionName="login"/>
          </viewControllerScriptsDirectory>
          <viewControllerScriptsDirectory forControllerName="User">
            <viewScriptFile forActionName="logout"/>
          </viewControllerScriptsDirectory>
          <viewControllerScriptsDirectory forControllerName="Page">
            <viewScriptFile forActionName="index"/>
          </viewControllerScriptsDirectory>
          <viewControllerScriptsDirectory forControllerName="Page">
            <viewScriptFile forActionName="create"/>
          </viewControllerScriptsDirectory>
          <viewControllerScriptsDirectory forControllerName="ProfileInformation">
            <viewScriptFile forActionName="index"/>
          </viewControllerScriptsDirectory>
          <viewControllerScriptsDirectory forControllerName="Relationship">
            <viewScriptFile forActionName="index"/>
          </viewControllerScriptsDirectory>
          <viewControllerScriptsDirectory forControllerName="Relationship">
            <viewScriptFile forActionName="pending"/>
          </viewControllerScriptsDirectory>
          <viewControllerScriptsDirectory forControllerName="Relationship">
            <viewScriptFile forActionName="request"/>
          </viewControllerScriptsDirectory>
          <viewControllerScriptsDirectory forControllerName="Relationship">
            <viewScriptFile forActionName="reject"/>
          </viewControllerScriptsDirectory>
          <viewControllerScriptsDirectory forControllerName="Relationship">
            <viewScriptFile forActionName="create"/>
          </viewControllerScriptsDirectory>
          <viewControllerScriptsDirectory forControllerName="Status">
            <viewScriptFile forActionName="index"/>
          </viewControllerScriptsDirectory>
          <viewControllerScriptsDirectory forControllerName="Status">
            <viewScriptFile forActionName="listStatuses"/>
          </viewControllerScriptsDirectory>
          <viewControllerScriptsDirectory forControllerName="Status">
            <viewScriptFile forActionName="createStatus"/>
          </viewControllerScriptsDirectory>
          <viewControllerScriptsDirectory forControllerName="Debug">
            <viewScriptFile forActionName="index"/>
          </viewControllerScriptsDirectory>
          <viewControllerScriptsDirectory forControllerName="Status">
            <viewScriptFile forActionName="list"/>
          </viewControllerScriptsDirectory>
          <viewControllerScriptsDirectory forControllerName="Status">
            <viewScriptFile forActionName="create"/>
          </viewControllerScriptsDirectory>
          <viewControllerScriptsDirectory forControllerName="Profile">
            <viewScriptFile forActionName="index"/>
          </viewControllerScriptsDirectory>
          <viewControllerScriptsDirectory forControllerName="Document">
            <viewScriptFile forActionName="index"/>
          </viewControllerScriptsDirectory>
          <viewControllerScriptsDirectory forControllerName="Wordlist">
            <viewScriptFile forActionName="index"/>
          </viewControllerScriptsDirectory>
          <viewControllerScriptsDirectory forControllerName="Classname">
            <viewScriptFile forActionName="index"/>
          </viewControllerScriptsDirectory>
          <viewControllerScriptsDirectory forControllerName="Index">
            <viewScriptFile forActionName="view"/>
          </viewControllerScriptsDirectory>
          <viewControllerScriptsDirectory forControllerName="User">
            <viewScriptFile forActionName="view"/>
          </viewControllerScriptsDirectory>
          <viewControllerScriptsDirectory forControllerName="Document">
            <viewScriptFile forActionName="create"/>
          </viewControllerScriptsDirectory>
          <viewControllerScriptsDirectory forControllerName="Search">
            <viewScriptFile forActionName="index"/>
          </viewControllerScriptsDirectory>
          <viewControllerScriptsDirectory forControllerName="Title">
            <viewScriptFile forActionName="index"/>
          </viewControllerScriptsDirectory>
          <viewControllerScriptsDirectory forControllerName="Document">
            <viewScriptFile forActionName="view"/>
          </viewControllerScriptsDirectory>
          <viewControllerScriptsDirectory forControllerName="Document">
            <viewScriptFile forActionName="edit"/>
          </viewControllerScriptsDirectory>
        </viewScriptsDirectory>
        <viewHelpersDirectory/>
        <viewFiltersDirectory enabled="false"/>
      </viewsDirectory>
      <bootstrapFile filesystemName="Bootstrap.php"/>
    </applicationDirectory>
    <dataDirectory enabled="false">
      <cacheDirectory enabled="false"/>
      <searchIndexesDirectory enabled="false"/>
      <localesDirectory enabled="false"/>
      <logsDirectory enabled="false"/>
      <sessionsDirectory enabled="false"/>
      <uploadsDirectory enabled="false"/>
    </dataDirectory>
    <docsDirectory>
      <file filesystemName="README.txt"/>
    </docsDirectory>
    <libraryDirectory>
      <zfStandardLibraryDirectory enabled="false"/>
    </libraryDirectory>
    <publicDirectory>
      <publicStylesheetsDirectory enabled="false"/>
      <publicScriptsDirectory enabled="false"/>
      <publicImagesDirectory enabled="false"/>
      <publicIndexFile filesystemName="index.php"/>
      <htaccessFile filesystemName=".htaccess"/>
    </publicDirectory>
    <projectProvidersDirectory enabled="false"/>
    <temporaryDirectory enabled="false"/>
    <testsDirectory>
      <testPHPUnitConfigFile filesystemName="phpunit.xml"/>
      <testPHPUnitBootstrapFile filesystemName="bootstrap.php"/>
      <testApplicationDirectory>
        <testApplicationControllerDirectory>
          <testApplicationControllerFile forControllerName="Index"/>
        </testApplicationControllerDirectory>
      </testApplicationDirectory>
      <testLibraryDirectory/>
    </testsDirectory>
  </projectDirectory>
</projectProfile>
